microconventions/__init__.py
microconventions/budget_conventions.py
microconventions/conventions.py
microconventions/horizon_conventions.py
microconventions/key_conventions.py
microconventions/leaderboard_conventions.py
microconventions/misc_conventions.py
microconventions/sep_conventions.py
microconventions/stats_conventions.py
microconventions/stream_conventions.py
microconventions/supporter.py
microconventions/type_conventions.py
microconventions/url_conventions.py
microconventions/value_conventions.py
microconventions/zcurve_conventions.py
microconventions-1.0.0.dist-info/METADATA
microconventions-1.0.0.dist-info/WHEEL
microconventions-1.0.0.dist-info/entry_points.txt
microconventions-1.0.0.dist-info/top_level.txt
microconventions-1.0.0.dist-info/RECORD
