Metadata-Version: 2.1
Name: microconventions
Version: 1.0.0
Summary: Conventions used at MicroPrediction.Org
Home-page: https://github.com/microprediction/microconventions
Author: microprediction
Author-email: info@microprediction.org
License: MIT
Platform: UNKNOWN
Classifier: License :: OSI Approved :: MIT License
Classifier: Programming Language :: Python :: 3
Classifier: Programming Language :: Python :: 3.7
Classifier: Programming Language :: Python :: 3.8
Classifier: Programming Language :: Python :: 3.9
Requires-Dist: muid (>=0.5.3)
Requires-Dist: getjson (>=2.0.0)
Requires-Dist: pymorton
Requires-Dist: tdigest
Requires-Dist: numpy
Requires-Dist: scipy
Requires-Dist: deepdiff
Requires-Dist: schema
